MANIFEST.in
README.rst
buildnotify.desktop
buildnotify.svg
buildnotifyapplet.py
setup.py
BuildNotify.egg-info/PKG-INFO
BuildNotify.egg-info/SOURCES.txt
BuildNotify.egg-info/dependency_links.txt
BuildNotify.egg-info/requires.txt
BuildNotify.egg-info/top_level.txt
buildnotifylib/__init__.py
buildnotifylib/app_menu.py
buildnotifylib/app_notification.py
buildnotifylib/app_ui.py
buildnotifylib/build_icons.py
buildnotifylib/buildnotify.py
buildnotifylib/config.py
buildnotifylib/notifications.py
buildnotifylib/preferences.py
buildnotifylib/project_status_notification.py
buildnotifylib/server_configuration_dialog.py
buildnotifylib/serverconfig.py
buildnotifylib/version.py
buildnotifylib/core/__init__.py
buildnotifylib/core/background_event.py
buildnotifylib/core/continous_integration_server.py
buildnotifylib/core/distance_of_time.py
buildnotifylib/core/filtered_continuous_integration_server.py
buildnotifylib/core/http_connection.py
buildnotifylib/core/keystore.py
buildnotifylib/core/project.py
buildnotifylib/core/projects.py
buildnotifylib/core/repeat_timed_event.py
buildnotifylib/core/response.py
buildnotifylib/core/timed_event.py
buildnotifylib/generated/__init__.py
buildnotifylib/generated/icons_rc.py
buildnotifylib/generated/preferences_ui.py
buildnotifylib/generated/server_configuration_ui.py