Metadata-Version: 1.1
Name: BuildNotify
Version: 2.0.0
Summary: Cruise Control build monitor for Windows/Linux/Mac
Home-page: https://anaynayak.github.io/buildnotify/
Author: Anay Nayak
Author-email: anayak007@gmail.com
License: GPL v3
Keywords: cctray ccmenu buildnotify ubuntu linux cruisecontrol continuous integration ci
Platform: UNKNOWN
Classifier: Intended Audience :: Developers
Classifier: Development Status :: 5 - Production/Stable
Classifier: License :: OSI Approved :: GNU General Public License v3 (GPLv3)
Classifier: Topic :: Software Development
Classifier: Programming Language :: Python
Classifier: Intended Audience :: Developers
Classifier: Intended Audience :: End Users/Desktop
Classifier: Environment :: X11 Applications :: Qt
Classifier: Topic :: Software Development :: Build Tools
Classifier: Topic :: Software Development :: User Interfaces
Classifier: Topic :: Software Development :: Widget Sets
